constellat_broadcast_service
