Metadata-Version: 2.1
Name: constellat-broadcast-service
Version: 1.0.3
Summary: A sample Python project
Home-page: https://github.com/Constellat/constellat-broadcast-service
Author: Constellat
Author-email: constellat0928@gamil.com
Keywords: broadcast,broadcast-service
Classifier: Development Status :: 3 - Alpha
Classifier: Intended Audience :: Developers
Classifier: Topic :: Software Development :: Build Tools
Classifier: License :: OSI Approved :: MIT License
Classifier: Programming Language :: Python :: 3
Classifier: Programming Language :: Python :: 3.7
Classifier: Programming Language :: Python :: 3.8
Classifier: Programming Language :: Python :: 3.9
Classifier: Programming Language :: Python :: 3.10
Classifier: Programming Language :: Python :: 3 :: Only
Requires-Python: >=3.7, <4
